{
    "data": {
        "124": {
            "avg": {
                "avg": {
                    "diff": 0.081197500000002,
                    "value": "21.1686450000000"
                },
                "buy": {
                    "diff": 0.099947499999999,
                    "value": "20.749895000"
                },
                "sale": {
                    "diff": 0.062447500000001,
                    "value": "21.587395000"
                }
            },
            "commercial": {
                "avg": {
                    "diff": 0.074999999999999,
                    "value": "21.0749999995000"
                },
                "buy": {
                    "diff": 0.099999999999998,
                    "value": "20.516666666"
                },
                "sale": {
                    "diff": 0.050000000000001,
                    "value": "21.633333333"
                }
            },
            "government": {
                "avg": {
                    "diff": 0.099790000000002,
                    "value": "21.4495800000000"
                },
                "buy": {
                    "diff": 0.099790000000002,
                    "value": "21.449580000"
                },
                "sale": {
                    "diff": 0.099790000000002,
                    "value": "21.449580000"
                }
            }
        },
        "392": {
            "avg": {
                "avg": {
                    "diff": -0.000745,
                    "value": "0.2489700000000"
                },
                "buy": {
                    "diff": -0.000495,
                    "value": "0.245720000"
                },
                "sale": {
                    "diff": -0.00099500000000002,
                    "value": "0.252220000"
                }
            },
            "commercial": {
                "avg": {
                    "diff": -0.0005,
                    "value": "0.2465000000000"
                },
                "buy": {
                    "diff": 0,
                    "value": "0.240000000"
                },
                "sale": {
                    "diff": -0.001,
                    "value": "0.253000000"
                }
            },
            "government": {
                "avg": {
                    "diff": -0.00098999999999999,
                    "value": "0.2514400000000"
                },
                "buy": {
                    "diff": -0.00098999999999999,
                    "value": "0.251440000"
                },
                "sale": {
                    "diff": -0.00098999999999999,
                    "value": "0.251440000"
                }
            }
        },
        "643": {
            "avg": {
                "avg": {
                    "diff": 0.001271071,
                    "value": "0.3655574995000"
                },
                "buy": {
                    "diff": 0.00052285700000004,
                    "value": "0.343455714"
                },
                "sale": {
                    "diff": 0.002019285,
                    "value": "0.387659285"
                }
            },
            "black": {
                "avg": {
                    "diff": 0.002525,
                    "value": "0.4064250000000"
                },
                "buy": {
                    "diff": 0.0023,
                    "value": "0.405000000"
                },
                "sale": {
                    "diff": 0.00275,
                    "value": "0.407850000"
                }
            },
            "commercial": {
                "avg": {
                    "diff": 0.00090909100000003,
                    "value": "0.3543863635000"
                },
                "buy": {
                    "diff": 0,
                    "value": "0.326440909"
                },
                "sale": {
                    "diff": 0.001818182,
                    "value": "0.382331818"
                }
            },
            "government": {
                "avg": {
                    "diff": 0.00132,
                    "value": "0.4028300000000"
                },
                "buy": {
                    "diff": 0.00132,
                    "value": "0.402830000"
                },
                "sale": {
                    "diff": 0.00132,
                    "value": "0.402830000"
                }
            },
            "interbank": {
                "avg": {
                    "diff": 0.00395,
                    "value": "0.4103000000000"
                },
                "buy": {
                    "diff": 0.0037,
                    "value": "0.409700000"
                },
                "sale": {
                    "diff": 0.0042,
                    "value": "0.410900000"
                }
            }
        },
        "756": {
            "avg": {
                "avg": {
                    "diff": 0.036053750000001,
                    "value": "28.6251937500000"
                },
                "buy": {
                    "diff": 0.02542875,
                    "value": "28.111443750"
                },
                "sale": {
                    "diff": 0.046678749999998,
                    "value": "29.138943750"
                }
            },
            "commercial": {
                "avg": {
                    "diff": 0.047857142999998,
                    "value": "28.6014285710000"
                },
                "buy": {
                    "diff": 0.035714286000001,
                    "value": "28.014285714"
                },
                "sale": {
                    "diff": 0.059999999999999,
                    "value": "29.188571428"
                }
            },
            "government": {
                "avg": {
                    "diff": -0.046569999999999,
                    "value": "28.7915500000000"
                },
                "buy": {
                    "diff": -0.046569999999999,
                    "value": "28.791550000"
                },
                "sale": {
                    "diff": -0.046569999999999,
                    "value": "28.791550000"
                }
            }
        },
        "826": {
            "avg": {
                "avg": {
                    "diff": 0.035073333500002,
                    "value": "36.1477433330000"
                },
                "buy": {
                    "diff": 0.042295554999995,
                    "value": "35.461076666"
                },
                "sale": {
                    "diff": 0.027851112,
                    "value": "36.834410000"
                }
            },
            "commercial": {
                "avg": {
                    "diff": 0.044375000000002,
                    "value": "36.1075000000000"
                },
                "buy": {
                    "diff": 0.052500000000002,
                    "value": "35.335000000"
                },
                "sale": {
                    "diff": 0.036250000000003,
                    "value": "36.880000000"
                }
            },
            "government": {
                "avg": {
                    "diff": -0.039340000000003,
                    "value": "36.4696900000000"
                },
                "buy": {
                    "diff": -0.039340000000003,
                    "value": "36.469690000"
                },
                "sale": {
                    "diff": -0.039340000000003,
                    "value": "36.469690000"
                }
            }
        },
        "840": {
            "avg": {
                "avg": {
                    "diff": 0.006374375,
                    "value": "28.0740375000000"
                },
                "buy": {
                    "diff": 0.010811875000002,
                    "value": "27.935287500"
                },
                "sale": {
                    "diff": 0.0019368750000019,
                    "value": "28.212787500"
                }
            },
            "black": {
                "avg": {
                    "diff": 0.026500000000002,
                    "value": "28.0985000000000"
                },
                "buy": {
                    "diff": 0.022500000000001,
                    "value": "28.068500000"
                },
                "sale": {
                    "diff": 0.0305,
                    "value": "28.128500000"
                }
            },
            "commercial": {
                "avg": {
                    "diff": 0.0049999995000007,
                    "value": "28.0703846145000"
                },
                "buy": {
                    "diff": 0.011538461000001,
                    "value": "27.903846153"
                },
                "sale": {
                    "diff": -0.0015384619999992,
                    "value": "28.236923076"
                }
            },
            "government": {
                "avg": {
                    "diff": -0.069510000000001,
                    "value": "28.0261000000000"
                },
                "buy": {
                    "diff": -0.069510000000001,
                    "value": "28.026100000"
                },
                "sale": {
                    "diff": -0.069510000000001,
                    "value": "28.026100000"
                }
            },
            "interbank": {
                "avg": {
                    "diff": 0.079999999999998,
                    "value": "28.1450000000000"
                },
                "buy": {
                    "diff": 0.07,
                    "value": "28.120000000"
                },
                "sale": {
                    "diff": 0.090000000000003,
                    "value": "28.170000000"
                }
            }
        },
        "978": {
            "avg": {
                "avg": {
                    "diff": 0.061819999999997,
                    "value": "32.5720800000000"
                },
                "buy": {
                    "diff": 0.069557499999995,
                    "value": "32.288373750"
                },
                "sale": {
                    "diff": 0.0540825,
                    "value": "32.855786250"
                }
            },
            "black": {
                "avg": {
                    "diff": 0.030450000000002,
                    "value": "32.5954500000000"
                },
                "buy": {
                    "diff": 0.026649999999997,
                    "value": "32.545950000"
                },
                "sale": {
                    "diff": 0.03425,
                    "value": "32.644950000"
                }
            },
            "commercial": {
                "avg": {
                    "diff": 0.065769230999997,
                    "value": "32.5688461535000"
                },
                "buy": {
                    "diff": 0.076153846000004,
                    "value": "32.225384615"
                },
                "sale": {
                    "diff": 0.055384615999998,
                    "value": "32.912307692"
                }
            },
            "government": {
                "avg": {
                    "diff": -0.049630000000001,
                    "value": "32.4682300000000"
                },
                "buy": {
                    "diff": -0.049630000000001,
                    "value": "32.468230000"
                },
                "sale": {
                    "diff": -0.049630000000001,
                    "value": "32.468230000"
                }
            },
            "interbank": {
                "avg": {
                    "diff": 0.1533,
                    "value": "32.6946000000000"
                },
                "buy": {
                    "diff": 0.1459,
                    "value": "32.669800000"
                },
                "sale": {
                    "diff": 0.1607,
                    "value": "32.719400000"
                }
            }
        },
        "980": {
            "avg": null
        },
        "985": {
            "avg": {
                "avg": {
                    "diff": 0.0025220000000008,
                    "value": "7.4716820000000"
                },
                "buy": {
                    "diff": 0.011522,
                    "value": "7.250682000"
                },
                "sale": {
                    "diff": -0.0064780000000004,
                    "value": "7.692682000"
                }
            },
            "commercial": {
                "avg": {
                    "diff": 0.0062499999999996,
                    "value": "7.4562500000000"
                },
                "buy": {
                    "diff": 0.0175,
                    "value": "7.180000000"
                },
                "sale": {
                    "diff": -0.0049999999999999,
                    "value": "7.732500000"
                }
            },
            "government": {
                "avg": {
                    "diff": -0.01239,
                    "value": "7.5334100000000"
                },
                "buy": {
                    "diff": -0.01239,
                    "value": "7.533410000"
                },
                "sale": {
                    "diff": -0.01239,
                    "value": "7.533410000"
                }
            }
        }
    },
    "day": "13.09.2018",
    "status": "success"
}